py.typed
pyripgrep.pyi
pyripgrep/__init__.py
pyripgrep/__init__.pyi
pyripgrep/py.typed
pyripgrep/pyripgrep.abi3.so
ripgrep_python-0.1.0.dist-info/METADATA
ripgrep_python-0.1.0.dist-info/WHEEL
ripgrep_python-0.1.0.dist-info/licenses/LICENSE
ripgrep_python-0.1.0.dist-info/RECORD
