Metadata-Version: 2.4
Name: ripgrep-python
Version: 0.1.0
Classifier: Development Status :: 4 - Beta
Classifier: Intended Audience :: Developers
Classifier: Topic :: Text Processing :: General
Classifier: Topic :: Software Development :: Libraries :: Python Modules
Classifier: Programming Language :: Python :: 3
Classifier: Programming Language :: Python :: 3.8
Classifier: Programming Language :: Python :: 3.9
Classifier: Programming Language :: Python :: 3.10
Classifier: Programming Language :: Python :: 3.11
Classifier: Programming Language :: Python :: 3.12
Classifier: Programming Language :: Rust
Classifier: License :: OSI Approved :: MIT License
Classifier: Operating System :: OS Independent
License-File: LICENSE
Summary: A Python native binding for ripgrep
Keywords: ripgrep,search,grep,rust,regex,text-search
Author-email: LinXueyuanStdio <23211526+LinXueyuanStdio@users.noreply.github.com>
Requires-Python: >=3.8
Project-URL: Homepage, https://github.com/LinXueyuanStdio/ripgrep-python
Project-URL: Repository, https://github.com/LinXueyuanStdio/ripgrep-python
Project-URL: Issues, https://github.com/LinXueyuanStdio/ripgrep-python/issues
